Zack/__init__.py
Zack/hello.py
zackpkg-0.0.1.dist-info/licenses/LICENSE.txt
zackpkg-0.0.1.dist-info/METADATA
zackpkg-0.0.1.dist-info/WHEEL
zackpkg-0.0.1.dist-info/top_level.txt
zackpkg-0.0.1.dist-info/RECORD
