Metadata-Version: 2.4
Name: Zackpkg
Version: 0.0.1
Summary: library to print hello in my package
Author: ArabCodeX
Author-email: zakaria.ahmed6765@gmail.com
Keywords: python,Zack,Hello
Classifier: Development Status :: 1 - Planning
Classifier: Intended Audience :: Developers
Classifier: Programming Language :: Python :: 3
Classifier: Operating System :: Unix
Classifier: Operating System :: MacOS :: MacOS X
Classifier: Operating System :: Microsoft :: Windows
License-File: LICENSE.txt
Dynamic: author
Dynamic: author-email
Dynamic: classifier
Dynamic: description
Dynamic: description-content-type
Dynamic: keywords
Dynamic: license-file
Dynamic: summary
